memory_monitor_cli/__init__.py
memory_monitor_cli/__main__.py
memory_monitor_cli-0.1.3.dist-info/LICENSE
memory_monitor_cli-0.1.3.dist-info/METADATA
memory_monitor_cli-0.1.3.dist-info/WHEEL
memory_monitor_cli-0.1.3.dist-info/entry_points.txt
memory_monitor_cli-0.1.3.dist-info/top_level.txt
memory_monitor_cli-0.1.3.dist-info/RECORD
