Metadata-Version: 2.1
Name: memory-monitor-cli
Version: 0.1.3
Summary: Memory Monitor CLI
Home-page: https://github.com/guallo/memory-monitor-cli
Author: The memory-monitor-cli Authors
Author-email: guallo.username@gmail.com
License: UNKNOWN
Platform: UNKNOWN
Classifier: Programming Language :: Python :: 3
Classifier: License :: OSI Approved :: MIT License
Classifier: Operating System :: OS Independent
Requires-Python: >=3.6
Requires-Dist: psutil
Requires-Dist: plotext
Requires-Dist: watchdog
